setup.py
pyyamlconfig/__init__.py
pyyamlconfig/load_config.py
pyyamlconfig.egg-info/PKG-INFO
pyyamlconfig.egg-info/SOURCES.txt
pyyamlconfig.egg-info/dependency_links.txt
pyyamlconfig.egg-info/requires.txt
pyyamlconfig.egg-info/top_level.txt