Metadata-Version: 1.1
Name: pyyamlconfig
Version: 0.1.10
Summary: Load configuration file in yaml format
Home-page: https://github.com/marhag87/pyyamlconfig
Author: marhag87
Author-email: marhag87@gmail.com
License: WTFPL
Platform: UNKNOWN
Classifier: Development Status :: 4 - Beta
Classifier: Intended Audience :: Developers
Classifier: Programming Language :: Python :: 3
